MANIFEST.in
README.rst
setup.py
docs/HISTORY.txt
docs/LICENSE.GPL
docs/LICENSE.txt
ftw/__init__.py
ftw.publisher.controlling.egg-info/PKG-INFO
ftw.publisher.controlling.egg-info/SOURCES.txt
ftw.publisher.controlling.egg-info/dependency_links.txt
ftw.publisher.controlling.egg-info/entry_points.txt
ftw.publisher.controlling.egg-info/namespace_packages.txt
ftw.publisher.controlling.egg-info/not-zip-safe
ftw.publisher.controlling.egg-info/requires.txt
ftw.publisher.controlling.egg-info/top_level.txt
ftw/publisher/__init__.py
ftw/publisher/controlling/__init__.py
ftw/publisher/controlling/adapters.py
ftw/publisher/controlling/configure.zcml
ftw/publisher/controlling/interfaces.py
ftw/publisher/controlling/profiles.zcml
ftw/publisher/controlling/utils.py
ftw/publisher/controlling/browser/__init__.py
ftw/publisher/controlling/browser/configure.zcml
ftw/publisher/controlling/browser/receiver/__init__.py
ftw/publisher/controlling/browser/receiver/configure.zcml
ftw/publisher/controlling/browser/receiver/jsonviews.py
ftw/publisher/controlling/browser/sender/__init__.py
ftw/publisher/controlling/browser/sender/configure.zcml
ftw/publisher/controlling/browser/sender/controlling.pt
ftw/publisher/controlling/browser/sender/element-listing.pt
ftw/publisher/controlling/browser/sender/views.py
ftw/publisher/controlling/browser/sender/resources/configlet_icon.gif
ftw/publisher/controlling/browser/sender/resources/element-listing.pt
ftw/publisher/controlling/locales/ftw.publisher.controlling.pot
ftw/publisher/controlling/locales/de/LC_MESSAGES/ftw.publisher.controlling.po
ftw/publisher/controlling/profiles/default/actionicons.xml
ftw/publisher/controlling/profiles/default/actions.xml
ftw/publisher/controlling/profiles/default/controlpanel.xml
ftw/publisher/controlling/profiles/default/metadata.xml