Metadata-Version: 2.1
Name: ftw.publisher.controlling
Version: 1.3.0
Summary: An ftw.publisher addon for statistics on published objects in a workflow based setup.
Home-page: https://github.com/4teamwork/ftw.publisher.controlling
Author: 4teamwork AG
Author-email: mailto:info@4teamwork.ch
License: GPL2
Keywords: ftw publisher controlling
Platform: UNKNOWN
Classifier: Framework :: Plone
Classifier: Framework :: Plone :: 4.3
Classifier: Framework :: Plone :: 5.1
Classifier: License :: OSI Approved :: GNU General Public License v2 (GPLv2)
Classifier: Programming Language :: Python
Classifier: Topic :: Software Development :: Libraries :: Python Modules
Provides-Extra: tests
Provides-Extra: sender
